textbook/__init__.py
textbook/dataset.py
textbook/renderers.py
textbook/templates.py
textbook/transforms_video.py
textbook/utils.py
textbook-0.3.10.dist-info/METADATA
textbook-0.3.10.dist-info/WHEEL
textbook-0.3.10.dist-info/top_level.txt
textbook-0.3.10.dist-info/RECORD
