Metadata-Version: 2.1
Name: textbook
Version: 0.3.10
Summary: Text classification datasets
Home-page: https://github.com/ChenghaoMou/textbook
Author: Chenghao
Author-email: mouchenghao@gmail.com
License: UNKNOWN
Platform: UNKNOWN
Classifier: Programming Language :: Python :: 3
Classifier: License :: OSI Approved :: MIT License
Classifier: Operating System :: MacOS :: MacOS X
Requires-Python: >=3.7.0
Requires-Dist: torch
Requires-Dist: transformers
Requires-Dist: torchvision
Requires-Dist: av
Requires-Dist: pandas
Requires-Dist: tqdm
Requires-Dist: loguru
Requires-Dist: numpy
